diva/__init__.py
diva/component/__init__.py
diva/component/activity_recognition/__init__.py
diva/component/activity_recognition/activity_classifier.py
diva/component/object_detection/__init__.py
diva/component/object_detection/object_detector.py
diva/data_store/__init__.py
diva/data_store/frame_store/__init__.py
diva/data_store/frame_store/frame_store.py
diva/data_type/__init__.py
diva/data_type/activity/__init__.py
diva/data_type/activity/activity.py
diva/data_type/activity/activity_factory.py
diva/data_type/activity/activity_functions.py
diva/data_type/activity/activity_proposal.py
diva/data_type/activity/activity_summary.py
diva/data_type/bounding_box/__init__.py
diva/data_type/bounding_box/bouding_box_summary.py
diva/data_type/bounding_box/bounding_box.py
diva/data_type/bounding_box/bounding_box_factory.py
diva/data_type/bounding_box/bounding_box_functions.py
diva/data_type/experiment/__init__.py
diva/data_type/experiment/experiment.py
diva/data_type/frame/__init__.py
diva/data_type/frame/frame.py
diva/data_type/frame/frame_functions.py
diva/data_type/frame/frame_summary.py
diva/data_type/frame/modality.py
diva/data_type/object/__init__.py
diva/data_type/object/object.py
diva/data_type/object/object_detection.py
diva/data_type/object/object_factory.py
diva/data_type/object/object_functions.py
diva/data_type/object/object_summary.py
diva/data_type/temporal_range/__init__.py
diva/data_type/temporal_range/temporal_range.py
diva/data_type/temporal_range/temporal_range_functions.py
diva/data_type/temporal_range/temporal_range_summary.py
diva/data_type/trajectory/__init__.py
diva/data_type/trajectory/trajectory.py
diva/data_type/trajectory/trajectory_factory.py
diva/data_type/trajectory/trajectory_functions.py
diva/data_type/trajectory/trajectory_summary.py
diva/data_type/video/__init__.py
diva/data_type/video/video.py
diva/data_type/video/video_summary.py
diva/dataset/__init__.py
diva/dataset/diva.py
diva/dataset/something_something.py
diva/visualization/__init__.py
diva_frater-0.1.12.dist-info/METADATA
diva_frater-0.1.12.dist-info/WHEEL
diva_frater-0.1.12.dist-info/top_level.txt
diva_frater-0.1.12.dist-info/RECORD
