Metadata-Version: 2.1
Name: diva-frater
Version: 0.1.12
Summary: DIVA Frater library containing data types, base Component classes, and visualization tools
Home-page: https://github.com/frater/diva
Author: John Henning
Author-email: john.l.henning@ibm.com
License: MIT
Platform: UNKNOWN
Requires-Python: >=3.6
Requires-Dist: opencv-python
Requires-Dist: sortedcontainers
Requires-Dist: frater
